amplitude_experiment/__init__.py
amplitude_experiment/connection_pool.py
amplitude_experiment/cookie.py
amplitude_experiment/exception.py
amplitude_experiment/factory.py
amplitude_experiment/server_zone.py
amplitude_experiment/user.py
amplitude_experiment/variant.py
amplitude_experiment/version.py
amplitude_experiment/__pycache__/__init__.cpython-38.pyc
amplitude_experiment/__pycache__/connection_pool.cpython-38.pyc
amplitude_experiment/__pycache__/cookie.cpython-38.pyc
amplitude_experiment/__pycache__/exception.cpython-38.pyc
amplitude_experiment/__pycache__/factory.cpython-38.pyc
amplitude_experiment/__pycache__/server_zone.cpython-38.pyc
amplitude_experiment/__pycache__/user.cpython-38.pyc
amplitude_experiment/__pycache__/variant.cpython-38.pyc
amplitude_experiment/__pycache__/version.cpython-38.pyc
amplitude_experiment/assignment/__init__.py
amplitude_experiment/assignment/assignment.py
amplitude_experiment/assignment/assignment_config.py
amplitude_experiment/assignment/assignment_filter.py
amplitude_experiment/assignment/assignment_service.py
amplitude_experiment/assignment/__pycache__/__init__.cpython-38.pyc
amplitude_experiment/assignment/__pycache__/assignment.cpython-38.pyc
amplitude_experiment/assignment/__pycache__/assignment_config.cpython-38.pyc
amplitude_experiment/assignment/__pycache__/assignment_filter.cpython-38.pyc
amplitude_experiment/assignment/__pycache__/assignment_service.cpython-38.pyc
amplitude_experiment/cohort/cohort.py
amplitude_experiment/cohort/cohort_download_api.py
amplitude_experiment/cohort/cohort_loader.py
amplitude_experiment/cohort/cohort_storage.py
amplitude_experiment/cohort/cohort_sync_config.py
amplitude_experiment/cohort/__pycache__/cohort.cpython-38.pyc
amplitude_experiment/cohort/__pycache__/cohort_download_api.cpython-38.pyc
amplitude_experiment/cohort/__pycache__/cohort_loader.cpython-38.pyc
amplitude_experiment/cohort/__pycache__/cohort_storage.cpython-38.pyc
amplitude_experiment-1.10.1.dist-info/LICENSE
amplitude_experiment-1.10.1.dist-info/METADATA
amplitude_experiment-1.10.1.dist-info/WHEEL
amplitude_experiment-1.10.1.dist-info/top_level.txt
amplitude_experiment-1.10.1.dist-info/RECORD
