Metadata-Version: 2.1
Name: amplitude-experiment
Version: 1.10.1
Summary: The official Amplitude Experiment Python SDK for server-side instrumentation.
Home-page: https://github.com/amplitude/experiment-python-server
Author: Amplitude Inc.
Author-email: sdk.dev@amplitude.com
License: MIT License
Project-URL: Bug Reports, https://github.com/amplitude/experiment-python-server/issues
Project-URL: Source, https://github.com/amplitude/experiment-python-server
Project-URL: Developer Doc, https://www.docs.developers.amplitude.com/experiment/sdks/python-sdk/
Keywords: amplitude,python,backend
Classifier: Development Status :: 4 - Beta
Classifier: Intended Audience :: Developers
Classifier: License :: OSI Approved :: MIT License
Classifier: Programming Language :: Python :: 3
Classifier: Programming Language :: Python :: 3.6
Classifier: Programming Language :: Python :: 3.7
Classifier: Programming Language :: Python :: 3.8
Classifier: Programming Language :: Python :: 3.9
Classifier: Programming Language :: Python :: 3.10
Requires-Python: >=3.6, <4
License-File: LICENSE
Requires-Dist: dataclasses-json >=0.6.7
Requires-Dist: amplitude-analytics >=1.1.1
Requires-Dist: sseclient-py ~=1.8.0
